{
  "basics": {
    "name": "Coltin-Kai Kaupiko",
    "label": "Student",
    "picture": "https://Coltin-Kai.github.io/images/MyFace.jpg",
    "email": "coltinkaikaupiko@gmail.com",
    "phone": "",
    "website": "https://Coltin-Kai.github.io",
    "summary": "I am studying for a B.S. in Computer Science in the Department of Information and Computer Sciences at the University of Hawaii at Manoua. I expect to graduate in Spring 2023.",
    "location": {
      "address": "",
      "postalCode": "96744",
      "city": "Kaneohe",
      "countryCode": "USA",
      "region": "Hawaii"
    },
    "profiles": [
      {
        "network": "github",
        "username": "Coltin-Kai",
        "url": "https://github.com/Coltin-Kai/Coltin-Kai.github.io"
      },
      {
        "network": "linkedin",
        "username": "Coltin-Kai Kaupiko",
        "url": "https://www.linkedin.com/in/coltin-kai-kaupiko/"
      }
    ]
  },
  "interests": [
    {
      "name": "Computer Graphics",
      "keywords": [
      ]
    },
    {
      "name": "Game Engines",
      "keywords": [
      ]
    },
    {
      "name": "Software Development",
      "keywords": [
      ]
    }
  ],
  "skills": [
    {
      "name": "Languages and Frameworks",
      "level": "",
      "keywords": [
        "C",
        "C++",
        "Java",
        "C#",
        "Lua",
        "XML"
      ]
    },
    {
      "name": "Toolsets/OS",
      "level": "",
      "keywords": [
        "Windows",
        "Visual Studio",
        "Git/GitHub",
      ]
    }
  ],
  "education": [
    {
      "institution": "University of Hawaii at Manoa, Honolulu, HI",
      "area": "Computer Science (expected Spring, 2023)",
      "studyType": "B.S.",
      "startDate": "2019-09-01",
      "endDate": "Present",
      "gpa": "3.51",
      "courses": [
      ]
    }
  ],
  "volunteer": [
    {
      "organization": "Ronald McDonald House Charity",
      "website": "https://www.ronaldhousehawaii.org/",
      "position": "Volunteer",
      "startDate": "2018-11-25",
      "endDate": "2018-12-9",
      "summary": "Worked with a team to remove pearls from clams to help profit the organization",
      "highlights": ["Dissucssed and organized ourselves to work efficiently as a team"
      ]
    },
  ],
}
